gcs_aio_mapper/__init__.py
gcs_aio_mapper/store.py
gcs_aio_mapper-0.1.0.dist-info/LICENSE
gcs_aio_mapper-0.1.0.dist-info/WHEEL
gcs_aio_mapper-0.1.0.dist-info/METADATA
gcs_aio_mapper-0.1.0.dist-info/RECORD
