Metadata-Version: 2.1
Name: gcs-aio-mapper
Version: 0.1.0
Summary: An mutable mapping interface to GCS leveraging asyncio
Home-page: https://github.com/nbren12/gcs_aio_mapper
License: MIT
Author: Noah D. Brenowitz
Author-email: nbren12@gmail.com
Requires-Python: >=3.7,<4.0
Classifier: License :: OSI Approved :: MIT License
Classifier: Programming Language :: Python :: 3
Classifier: Programming Language :: Python :: 3.7
Classifier: Programming Language :: Python :: 3.8
Requires-Dist: aiohttp (>=3.6.2,<4.0.0)
Requires-Dist: gcloud-aio-storage (>=5.2.2,<6.0.0)
Requires-Dist: google-cloud-storage (>=1.26.0,<2.0.0)
Requires-Dist: pylint (>=2.4.4,<3.0.0)
Project-URL: Repository, https://github.com/nbren12/gcs_aio_mapper
